{
  "generated_at": "2026-04-27T00:31:15.617097+09:00",
  "predictions": [
    {
      "date": "2026-04-27",
      "temp": 12.38,
      "humidity": 96.0,
      "wind": 3.62,
      "cloud": 81.5,
      "rain": 1.38,
      "weathercode": 61,
      "fog_probability": 0.009,
      "castle_probability": 0.129,
      "castle_event_probability": 0.002,
      "event": "None"
    },
    {
      "date": "2026-04-28",
      "temp": 14.28,
      "humidity": 72.0,
      "wind": 7.83,
      "cloud": 63.0,
      "rain": 0.0,
      "weathercode": 1,
      "fog_probability": 0.847,
      "castle_probability": 0.92,
      "castle_event_probability": 0.903,
      "event": "Castle"
    },
    {
      "date": "2026-04-29",
      "temp": 10.68,
      "humidity": 91.0,
      "wind": 3.08,
      "cloud": 60.0,
      "rain": 0.0,
      "weathercode": 2,
      "fog_probability": 0.584,
      "castle_probability": 0.508,
      "castle_event_probability": 0.123,
      "event": "FogOnly"
    },
    {
      "date": "2026-04-30",
      "temp": 10.07,
      "humidity": 85.5,
      "wind": 2.75,
      "cloud": 100.0,
      "rain": 0.0,
      "weathercode": 3,
      "fog_probability": 0.656,
      "castle_probability": 0.608,
      "castle_event_probability": 0.269,
      "event": "FogOnly"
    },
    {
      "date": "2026-05-01",
      "temp": 13.02,
      "humidity": 97.25,
      "wind": 5.17,
      "cloud": 100.0,
      "rain": 2.75,
      "weathercode": 63,
      "fog_probability": 0.098,
      "castle_probability": 0.472,
      "castle_event_probability": 0.009,
      "event": "None"
    },
    {
      "date": "2026-05-02",
      "temp": 11.6,
      "humidity": 79.0,
      "wind": 5.1,
      "cloud": 30.0,
      "rain": 0.0,
      "weathercode": 0,
      "fog_probability": 0.909,
      "castle_probability": 0.468,
      "castle_event_probability": 0.383,
      "event": "FogOnly"
    },
    {
      "date": "2026-05-03",
      "temp": 13.73,
      "humidity": 85.0,
      "wind": 2.83,
      "cloud": 99.75,
      "rain": 0.1,
      "weathercode": 51,
      "fog_probability": 0.069,
      "castle_probability": 0.217,
      "castle_event_probability": 0.004,
      "event": "None"
    },
    {
      "date": "2026-05-04",
      "temp": 15.7,
      "humidity": 54.5,
      "wind": 4.83,
      "cloud": 99.5,
      "rain": 0.0,
      "weathercode": 3,
      "fog_probability": 0.941,
      "castle_probability": 0.258,
      "castle_event_probability": 0.14,
      "event": "FogOnly"
    },
    {
      "date": "2026-05-05",
      "temp": 16.12,
      "humidity": 61.5,
      "wind": 2.2,
      "cloud": 0.0,
      "rain": 0.0,
      "weathercode": 0,
      "fog_probability": 0.883,
      "castle_probability": 0.099,
      "castle_event_probability": 0.041,
      "event": "FogOnly"
    },
    {
      "date": "2026-05-06",
      "temp": 14.47,
      "humidity": 89.25,
      "wind": 14.43,
      "cloud": 100.0,
      "rain": 2.4,
      "weathercode": 61,
      "fog_probability": 0.026,
      "castle_probability": 0.372,
      "castle_event_probability": 0.005,
      "event": "None"
    },
    {
      "date": "2026-05-07",
      "temp": 13.33,
      "humidity": 99.5,
      "wind": 16.88,
      "cloud": 100.0,
      "rain": 2.4,
      "weathercode": 61,
      "fog_probability": 0.048,
      "castle_probability": 0.083,
      "castle_event_probability": 0.002,
      "event": "None"
    },
    {
      "date": "2026-05-08",
      "temp": 16.73,
      "humidity": 70.25,
      "wind": 7.18,
      "cloud": 100.0,
      "rain": 0.0,
      "weathercode": 3,
      "fog_probability": 0.926,
      "castle_probability": 0.49,
      "castle_event_probability": 0.444,
      "event": "FogOnly"
    },
    {
      "date": "2026-05-09",
      "temp": 12.07,
      "humidity": 60.25,
      "wind": 2.0,
      "cloud": 2.5,
      "rain": 0.0,
      "weathercode": 0,
      "fog_probability": 0.763,
      "castle_probability": 0.472,
      "castle_event_probability": 0.229,
      "event": "FogOnly"
    },
    {
      "date": "2026-05-10",
      "temp": 14.2,
      "humidity": 69.25,
      "wind": 3.98,
      "cloud": 4.25,
      "rain": 0.0,
      "weathercode": 0,
      "fog_probability": 0.388,
      "castle_probability": 0.624,
      "castle_event_probability": 0.075,
      "event": "None"
    }
  ]
}