{
  "generated_at": "2026-02-07T13:14:19.475372+09:00",
  "predictions": [
    {
      "date": "2026-02-07",
      "temp": -1.55,
      "humidity": 82.5,
      "wind": 4.95,
      "cloud": 100.0,
      "rain": 0.0,
      "weathercode": 3,
      "fog_probability": 0.087,
      "castle_probability": 0.698,
      "castle_event_probability": 0.017,
      "event": "None"
    },
    {
      "date": "2026-02-08",
      "temp": -4.38,
      "humidity": 82.75,
      "wind": 5.47,
      "cloud": 89.0,
      "rain": 0.33,
      "weathercode": 73,
      "fog_probability": 0.006,
      "castle_probability": 0.748,
      "castle_event_probability": 0.011,
      "event": "None"
    },
    {
      "date": "2026-02-09",
      "temp": -4.8,
      "humidity": 92.75,
      "wind": 1.98,
      "cloud": 99.0,
      "rain": 0.3,
      "weathercode": 73,
      "fog_probability": 0.116,
      "castle_probability": 0.145,
      "castle_event_probability": 0.004,
      "event": "None"
    },
    {
      "date": "2026-02-10",
      "temp": -0.63,
      "humidity": 78.25,
      "wind": 7.75,
      "cloud": 33.0,
      "rain": 0.0,
      "weathercode": 0,
      "fog_probability": 0.502,
      "castle_probability": 0.807,
      "castle_event_probability": 0.289,
      "event": "FogOnly"
    },
    {
      "date": "2026-02-11",
      "temp": 4.9,
      "humidity": 93.0,
      "wind": 5.08,
      "cloud": 99.25,
      "rain": 0.4,
      "weathercode": 61,
      "fog_probability": 0.002,
      "castle_probability": 0.994,
      "castle_event_probability": 0.02,
      "event": "None"
    },
    {
      "date": "2026-02-12",
      "temp": 2.17,
      "humidity": 81.75,
      "wind": 2.65,
      "cloud": 55.0,
      "rain": 0.0,
      "weathercode": 1,
      "fog_probability": 0.467,
      "castle_probability": 0.612,
      "castle_event_probability": 0.111,
      "event": "None"
    },
    {
      "date": "2026-02-13",
      "temp": 1.98,
      "humidity": 82.0,
      "wind": 6.3,
      "cloud": 71.0,
      "rain": 0.0,
      "weathercode": 2,
      "fog_probability": 0.247,
      "castle_probability": 0.93,
      "castle_event_probability": 0.1,
      "event": "None"
    },
    {
      "date": "2026-02-14",
      "temp": 4.03,
      "humidity": 92.0,
      "wind": 5.53,
      "cloud": 96.25,
      "rain": 0.0,
      "weathercode": 3,
      "fog_probability": 0.139,
      "castle_probability": 0.989,
      "castle_event_probability": 0.056,
      "event": "None"
    },
    {
      "date": "2026-02-15",
      "temp": 4.38,
      "humidity": 71.75,
      "wind": 11.57,
      "cloud": 4.5,
      "rain": 0.0,
      "weathercode": 0,
      "fog_probability": 0.258,
      "castle_probability": 0.699,
      "castle_event_probability": 0.048,
      "event": "None"
    },
    {
      "date": "2026-02-16",
      "temp": 8.2,
      "humidity": 96.75,
      "wind": 4.68,
      "cloud": 100.0,
      "rain": 0.1,
      "weathercode": 3,
      "fog_probability": 0.22,
      "castle_probability": 0.911,
      "castle_event_probability": 0.078,
      "event": "None"
    },
    {
      "date": "2026-02-17",
      "temp": 6.85,
      "humidity": 82.0,
      "wind": 11.47,
      "cloud": 4.75,
      "rain": 0.0,
      "weathercode": 0,
      "fog_probability": 0.319,
      "castle_probability": 0.833,
      "castle_event_probability": 0.113,
      "event": "None"
    },
    {
      "date": "2026-02-18",
      "temp": 10.82,
      "humidity": 80.5,
      "wind": 24.62,
      "cloud": 100.0,
      "rain": 0.0,
      "weathercode": 3,
      "fog_probability": 0.262,
      "castle_probability": 0.603,
      "castle_event_probability": 0.034,
      "event": "None"
    },
    {
      "date": "2026-02-19",
      "temp": 2.38,
      "humidity": 89.0,
      "wind": 12.12,
      "cloud": 100.0,
      "rain": 0.25,
      "weathercode": 51,
      "fog_probability": 0.001,
      "castle_probability": 0.686,
      "castle_event_probability": 0.009,
      "event": "None"
    },
    {
      "date": "2026-02-20",
      "temp": -0.27,
      "humidity": 70.25,
      "wind": 6.9,
      "cloud": 2.75,
      "rain": 0.0,
      "weathercode": 0,
      "fog_probability": 0.892,
      "castle_probability": 0.55,
      "castle_event_probability": 0.503,
      "event": "Castle"
    }
  ]
}