[
  {
    "date": "2026-03-20",
    "temp": 1.2,
    "humidity": 89.5,
    "wind": 2.925,
    "cloud": 14.25,
    "rain": 0.0,
    "weathercode": 0
  },
  {
    "date": "2026-03-21",
    "temp": -0.125,
    "humidity": 69.25,
    "wind": 3.1500000000000004,
    "cloud": 0.0,
    "rain": 0.0,
    "weathercode": 0
  },
  {
    "date": "2026-03-22",
    "temp": 3.325,
    "humidity": 46.0,
    "wind": 7.3500000000000005,
    "cloud": 4.75,
    "rain": 0.0,
    "weathercode": 0
  },
  {
    "date": "2026-03-23",
    "temp": 9.425,
    "humidity": 89.75,
    "wind": 4.45,
    "cloud": 99.75,
    "rain": 1.3250000000000002,
    "weathercode": 80
  },
  {
    "date": "2026-03-24",
    "temp": 4.949999999999999,
    "humidity": 87.25,
    "wind": 3.4250000000000003,
    "cloud": 71.0,
    "rain": 0.0,
    "weathercode": 1
  },
  {
    "date": "2026-03-25",
    "temp": 6.85,
    "humidity": 86.25,
    "wind": 2.95,
    "cloud": 100.0,
    "rain": 0.0,
    "weathercode": 3
  },
  {
    "date": "2026-03-26",
    "temp": 10.175,
    "humidity": 86.25,
    "wind": 2.075,
    "cloud": 96.25,
    "rain": 0.0,
    "weathercode": 3
  },
  {
    "date": "2026-03-27",
    "temp": 6.949999999999999,
    "humidity": 91.25,
    "wind": 4.125,
    "cloud": 40.25,
    "rain": 0.0,
    "weathercode": 0
  },
  {
    "date": "2026-03-28",
    "temp": 10.425,
    "humidity": 62.25,
    "wind": 8.274999999999999,
    "cloud": 100.0,
    "rain": 0.0,
    "weathercode": 3
  },
  {
    "date": "2026-03-29",
    "temp": 10.175,
    "humidity": 71.0,
    "wind": 5.0,
    "cloud": 100.0,
    "rain": 0.0,
    "weathercode": 3
  },
  {
    "date": "2026-03-30",
    "temp": 9.45,
    "humidity": 93.5,
    "wind": 3.375,
    "cloud": 100.0,
    "rain": 0.0,
    "weathercode": 3
  },
  {
    "date": "2026-03-31",
    "temp": 7.175,
    "humidity": 83.0,
    "wind": 4.45,
    "cloud": 17.25,
    "rain": 0.0,
    "weathercode": 0
  },
  {
    "date": "2026-04-01",
    "temp": 10.875,
    "humidity": 84.75,
    "wind": 13.425,
    "cloud": 100.0,
    "rain": 0.15,
    "weathercode": 51
  },
  {
    "date": "2026-04-02",
    "temp": 4.85,
    "humidity": 85.75,
    "wind": 7.025,
    "cloud": 95.0,
    "rain": 0.05,
    "weathercode": 3
  }
]