[
  {
    "date": "2025-12-10",
    "temp": 3.9750000000000005,
    "humidity": 83.0,
    "wind": 4.25,
    "cloud": 66.75,
    "rain": 0.0,
    "weathercode": 2
  },
  {
    "date": "2025-12-11",
    "temp": 5.125,
    "humidity": 74.0,
    "wind": 7.75,
    "cloud": 51.25,
    "rain": 0.0,
    "weathercode": 1
  },
  {
    "date": "2025-12-12",
    "temp": 1.375,
    "humidity": 75.25,
    "wind": 12.649999999999999,
    "cloud": 67.75,
    "rain": 0.025,
    "weathercode": 2
  },
  {
    "date": "2025-12-13",
    "temp": -1.25,
    "humidity": 80.75,
    "wind": 1.15,
    "cloud": 6.5,
    "rain": 0.0,
    "weathercode": 1
  },
  {
    "date": "2025-12-14",
    "temp": 7.699999999999999,
    "humidity": 87.75,
    "wind": 4.25,
    "cloud": 100.0,
    "rain": 1.1,
    "weathercode": 61
  },
  {
    "date": "2025-12-15",
    "temp": 4.324999999999999,
    "humidity": 91.25,
    "wind": 6.875,
    "cloud": 100.0,
    "rain": 1.1,
    "weathercode": 80
  },
  {
    "date": "2025-12-16",
    "temp": 4.175,
    "humidity": 73.75,
    "wind": 7.025,
    "cloud": 70.75,
    "rain": 0.0,
    "weathercode": 2
  },
  {
    "date": "2025-12-17",
    "temp": 1.9,
    "humidity": 83.0,
    "wind": 8.200000000000001,
    "cloud": 58.75,
    "rain": 0.0,
    "weathercode": 2
  },
  {
    "date": "2025-12-18",
    "temp": 3.625,
    "humidity": 94.25,
    "wind": 4.225,
    "cloud": 81.5,
    "rain": 0.0,
    "weathercode": 3
  },
  {
    "date": "2025-12-19",
    "temp": 1.375,
    "humidity": 68.75,
    "wind": 6.225,
    "cloud": 1.5,
    "rain": 0.0,
    "weathercode": 0
  },
  {
    "date": "2025-12-20",
    "temp": 3.45,
    "humidity": 66.75,
    "wind": 11.274999999999999,
    "cloud": 80.25,
    "rain": 0.0,
    "weathercode": 3
  },
  {
    "date": "2025-12-21",
    "temp": 7.975,
    "humidity": 80.0,
    "wind": 10.175,
    "cloud": 0.0,
    "rain": 0.0,
    "weathercode": 0
  },
  {
    "date": "2025-12-22",
    "temp": 9.95,
    "humidity": 84.5,
    "wind": 9.0,
    "cloud": 100.0,
    "rain": 0.0,
    "weathercode": 3
  },
  {
    "date": "2025-12-23",
    "temp": 10.525,
    "humidity": 89.0,
    "wind": 5.824999999999999,
    "cloud": 100.0,
    "rain": 0.0,
    "weathercode": 3
  }
]