{
  "generated_at": "2025-12-06T12:16:09.422027+09:00",
  "predictions": [
    {
      "date": "2025-12-06",
      "temp": 1.15,
      "humidity": 94.5,
      "wind": 7.45,
      "cloud": 49.5,
      "rain": 0.0,
      "weathercode": 1,
      "fog_probability": 0.849,
      "castle_probability": 0.713,
      "castle_event_probability": 0.69,
      "event": "Castle"
    },
    {
      "date": "2025-12-07",
      "temp": 4.33,
      "humidity": 76.25,
      "wind": 8.5,
      "cloud": 26.25,
      "rain": 0.0,
      "weathercode": 1,
      "fog_probability": 0.575,
      "castle_probability": 0.987,
      "castle_event_probability": 0.639,
      "event": "Castle"
    },
    {
      "date": "2025-12-08",
      "temp": 8.12,
      "humidity": 79.0,
      "wind": 6.93,
      "cloud": 39.75,
      "rain": 0.0,
      "weathercode": 1,
      "fog_probability": 0.199,
      "castle_probability": 0.918,
      "castle_event_probability": 0.078,
      "event": "None"
    },
    {
      "date": "2025-12-09",
      "temp": 3.75,
      "humidity": 85.25,
      "wind": 2.58,
      "cloud": 55.75,
      "rain": 0.0,
      "weathercode": 2,
      "fog_probability": 0.009,
      "castle_probability": 0.554,
      "castle_event_probability": 0.008,
      "event": "None"
    },
    {
      "date": "2025-12-10",
      "temp": 1.4,
      "humidity": 92.25,
      "wind": 4.7,
      "cloud": 40.25,
      "rain": 0.0,
      "weathercode": 1,
      "fog_probability": 0.655,
      "castle_probability": 0.981,
      "castle_event_probability": 0.755,
      "event": "Castle"
    },
    {
      "date": "2025-12-11",
      "temp": 4.42,
      "humidity": 86.25,
      "wind": 5.12,
      "cloud": 93.5,
      "rain": 0.0,
      "weathercode": 3,
      "fog_probability": 0.964,
      "castle_probability": 0.892,
      "castle_event_probability": 0.942,
      "event": "Castle"
    },
    {
      "date": "2025-12-12",
      "temp": 1.35,
      "humidity": 79.75,
      "wind": 2.43,
      "cloud": 39.25,
      "rain": 0.0,
      "weathercode": 1,
      "fog_probability": 0.096,
      "castle_probability": 0.694,
      "castle_event_probability": 0.02,
      "event": "None"
    },
    {
      "date": "2025-12-13",
      "temp": 0.05,
      "humidity": 75.25,
      "wind": 3.95,
      "cloud": 1.75,
      "rain": 0.0,
      "weathercode": 0,
      "fog_probability": 0.829,
      "castle_probability": 0.947,
      "castle_event_probability": 0.9,
      "event": "Castle"
    },
    {
      "date": "2025-12-14",
      "temp": 8.53,
      "humidity": 93.5,
      "wind": 14.17,
      "cloud": 100.0,
      "rain": 0.45,
      "weathercode": 51,
      "fog_probability": 0.018,
      "castle_probability": 0.576,
      "castle_event_probability": 0.009,
      "event": "None"
    },
    {
      "date": "2025-12-15",
      "temp": 2.67,
      "humidity": 94.25,
      "wind": 20.32,
      "cloud": 100.0,
      "rain": 0.45,
      "weathercode": 53,
      "fog_probability": 0.026,
      "castle_probability": 0.627,
      "castle_event_probability": 0.011,
      "event": "None"
    },
    {
      "date": "2025-12-16",
      "temp": 2.38,
      "humidity": 85.5,
      "wind": 5.82,
      "cloud": 81.75,
      "rain": 0.0,
      "weathercode": 2,
      "fog_probability": 0.901,
      "castle_probability": 0.857,
      "castle_event_probability": 0.891,
      "event": "Castle"
    },
    {
      "date": "2025-12-17",
      "temp": 5.92,
      "humidity": 96.75,
      "wind": 4.57,
      "cloud": 100.0,
      "rain": 0.3,
      "weathercode": 51,
      "fog_probability": 0.043,
      "castle_probability": 0.924,
      "castle_event_probability": 0.028,
      "event": "None"
    },
    {
      "date": "2025-12-18",
      "temp": 1.6,
      "humidity": 82.75,
      "wind": 4.15,
      "cloud": 7.0,
      "rain": 0.0,
      "weathercode": 0,
      "fog_probability": 0.943,
      "castle_probability": 0.84,
      "castle_event_probability": 0.906,
      "event": "Castle"
    },
    {
      "date": "2025-12-19",
      "temp": 3.2,
      "humidity": 66.0,
      "wind": 7.0,
      "cloud": 100.0,
      "rain": 0.0,
      "weathercode": 3,
      "fog_probability": 0.844,
      "castle_probability": 0.841,
      "castle_event_probability": 0.833,
      "event": "Castle"
    }
  ]
}