[
  {
    "date": "2026-04-09",
    "temp": 10.225,
    "humidity": 61.0,
    "wind": 13.8,
    "cloud": 13.0,
    "rain": 0.0,
    "weathercode": 0
  },
  {
    "date": "2026-04-10",
    "temp": 15.900000000000002,
    "humidity": 86.0,
    "wind": 15.099999999999998,
    "cloud": 82.0,
    "rain": 0.175,
    "weathercode": 2
  },
  {
    "date": "2026-04-11",
    "temp": 13.375,
    "humidity": 94.25,
    "wind": 6.2,
    "cloud": 73.0,
    "rain": 0.125,
    "weathercode": 51
  },
  {
    "date": "2026-04-12",
    "temp": 6.75,
    "humidity": 52.0,
    "wind": 2.8,
    "cloud": 0.0,
    "rain": 0.0,
    "weathercode": 0
  },
  {
    "date": "2026-04-13",
    "temp": 13.950000000000001,
    "humidity": 66.5,
    "wind": 4.475,
    "cloud": 70.25,
    "rain": 0.0,
    "weathercode": 2
  },
  {
    "date": "2026-04-14",
    "temp": 15.35,
    "humidity": 85.75,
    "wind": 3.7249999999999996,
    "cloud": 96.75,
    "rain": 0.05,
    "weathercode": 3
  },
  {
    "date": "2026-04-15",
    "temp": 12.475,
    "humidity": 96.0,
    "wind": 4.075,
    "cloud": 97.25,
    "rain": 0.05,
    "weathercode": 3
  },
  {
    "date": "2026-04-16",
    "temp": 9.075,
    "humidity": 63.5,
    "wind": 2.0999999999999996,
    "cloud": 43.0,
    "rain": 0.0,
    "weathercode": 1
  },
  {
    "date": "2026-04-17",
    "temp": 13.2,
    "humidity": 80.0,
    "wind": 7.175,
    "cloud": 15.5,
    "rain": 0.0,
    "weathercode": 0
  },
  {
    "date": "2026-04-18",
    "temp": 12.4,
    "humidity": 66.75,
    "wind": 5.9750000000000005,
    "cloud": 22.25,
    "rain": 0.0,
    "weathercode": 0
  },
  {
    "date": "2026-04-19",
    "temp": 13.025,
    "humidity": 79.75,
    "wind": 2.85,
    "cloud": 100.0,
    "rain": 0.0,
    "weathercode": 3
  },
  {
    "date": "2026-04-20",
    "temp": 13.4,
    "humidity": 87.25,
    "wind": 3.225,
    "cloud": 11.0,
    "rain": 0.0,
    "weathercode": 0
  },
  {
    "date": "2026-04-21",
    "temp": 13.5,
    "humidity": 61.25,
    "wind": 3.525,
    "cloud": 96.5,
    "rain": 0.0,
    "weathercode": 3
  },
  {
    "date": "2026-04-22",
    "temp": 13.7,
    "humidity": 87.25,
    "wind": 2.475,
    "cloud": 100.0,
    "rain": 0.05,
    "weathercode": 51
  }
]