{
  "generated_at": "2026-01-12T04:40:28.606636+09:00",
  "predictions": [
    {
      "date": "2026-01-12",
      "temp": -1.73,
      "humidity": 91.25,
      "wind": 3.5,
      "cloud": 97.25,
      "rain": 0.35,
      "weathercode": 73,
      "fog_probability": 0.474,
      "castle_probability": 0.313,
      "castle_event_probability": 0.03,
      "event": "None"
    },
    {
      "date": "2026-01-13",
      "temp": 2.5,
      "humidity": 74.75,
      "wind": 12.3,
      "cloud": 57.75,
      "rain": 0.0,
      "weathercode": 2,
      "fog_probability": 0.436,
      "castle_probability": 0.675,
      "castle_event_probability": 0.127,
      "event": "None"
    },
    {
      "date": "2026-01-14",
      "temp": 1.45,
      "humidity": 81.0,
      "wind": 5.65,
      "cloud": 85.5,
      "rain": 0.03,
      "weathercode": 3,
      "fog_probability": 0.528,
      "castle_probability": 0.994,
      "castle_event_probability": 0.567,
      "event": "Castle"
    },
    {
      "date": "2026-01-15",
      "temp": 2.9,
      "humidity": 77.5,
      "wind": 6.8,
      "cloud": 100.0,
      "rain": 0.0,
      "weathercode": 3,
      "fog_probability": 0.394,
      "castle_probability": 0.926,
      "castle_event_probability": 0.257,
      "event": "None"
    },
    {
      "date": "2026-01-16",
      "temp": 7.9,
      "humidity": 81.25,
      "wind": 3.98,
      "cloud": 76.0,
      "rain": 0.05,
      "weathercode": 2,
      "fog_probability": 0.11,
      "castle_probability": 0.98,
      "castle_event_probability": 0.048,
      "event": "None"
    },
    {
      "date": "2026-01-17",
      "temp": 4.25,
      "humidity": 93.25,
      "wind": 3.55,
      "cloud": 82.5,
      "rain": 0.0,
      "weathercode": 2,
      "fog_probability": 0.189,
      "castle_probability": 0.985,
      "castle_event_probability": 0.086,
      "event": "None"
    },
    {
      "date": "2026-01-18",
      "temp": 1.77,
      "humidity": 87.25,
      "wind": 1.38,
      "cloud": 48.5,
      "rain": 0.0,
      "weathercode": 1,
      "fog_probability": 0.814,
      "castle_probability": 0.426,
      "castle_event_probability": 0.224,
      "event": "FogOnly"
    },
    {
      "date": "2026-01-19",
      "temp": 4.25,
      "humidity": 73.0,
      "wind": 4.95,
      "cloud": 5.25,
      "rain": 0.0,
      "weathercode": 0,
      "fog_probability": 0.654,
      "castle_probability": 0.943,
      "castle_event_probability": 0.721,
      "event": "Castle"
    },
    {
      "date": "2026-01-20",
      "temp": 0.22,
      "humidity": 87.0,
      "wind": 10.35,
      "cloud": 100.0,
      "rain": 0.0,
      "weathercode": 3,
      "fog_probability": 0.685,
      "castle_probability": 0.87,
      "castle_event_probability": 0.678,
      "event": "Castle"
    },
    {
      "date": "2026-01-21",
      "temp": -3.32,
      "humidity": 88.0,
      "wind": 7.6,
      "cloud": 57.75,
      "rain": 0.35,
      "weathercode": 73,
      "fog_probability": 0.011,
      "castle_probability": 0.914,
      "castle_event_probability": 0.02,
      "event": "None"
    },
    {
      "date": "2026-01-22",
      "temp": -3.25,
      "humidity": 95.75,
      "wind": 5.8,
      "cloud": 100.0,
      "rain": 0.4,
      "weathercode": 73,
      "fog_probability": 0.054,
      "castle_probability": 0.902,
      "castle_event_probability": 0.026,
      "event": "None"
    },
    {
      "date": "2026-01-23",
      "temp": -1.73,
      "humidity": 96.25,
      "wind": 3.0,
      "cloud": 100.0,
      "rain": 0.1,
      "weathercode": 71,
      "fog_probability": 0.823,
      "castle_probability": 0.276,
      "castle_event_probability": 0.102,
      "event": "FogOnly"
    },
    {
      "date": "2026-01-24",
      "temp": -4.12,
      "humidity": 85.5,
      "wind": 8.4,
      "cloud": 71.5,
      "rain": 0.0,
      "weathercode": 2,
      "fog_probability": 0.593,
      "castle_probability": 0.588,
      "castle_event_probability": 0.191,
      "event": "FogOnly"
    },
    {
      "date": "2026-01-25",
      "temp": -2.58,
      "humidity": 87.75,
      "wind": 6.95,
      "cloud": 65.75,
      "rain": 0.0,
      "weathercode": 2,
      "fog_probability": 0.924,
      "castle_probability": 0.982,
      "castle_event_probability": 0.962,
      "event": "Castle"
    }
  ]
}