{
  "generated_at": "2026-07-04T21:13:29.087175+09:00",
  "predictions": [
    {
      "date": "2026-07-04",
      "temp": 22.5,
      "humidity": 84.25,
      "wind": 8.7,
      "cloud": 100.0,
      "rain": 0.0,
      "weathercode": 3,
      "fog_probability": 0.458,
      "castle_probability": 0.581,
      "castle_event_probability": 0.091,
      "event": "None"
    },
    {
      "date": "2026-07-05",
      "temp": 22.43,
      "humidity": 86.0,
      "wind": 3.53,
      "cloud": 81.25,
      "rain": 0.15,
      "weathercode": 2,
      "fog_probability": 0.217,
      "castle_probability": 0.164,
      "castle_event_probability": 0.005,
      "event": "None"
    },
    {
      "date": "2026-07-06",
      "temp": 22.58,
      "humidity": 84.75,
      "wind": 8.12,
      "cloud": 72.75,
      "rain": 1.25,
      "weathercode": 1,
      "fog_probability": 0.004,
      "castle_probability": 0.067,
      "castle_event_probability": 0.002,
      "event": "None"
    },
    {
      "date": "2026-07-07",
      "temp": 21.75,
      "humidity": 85.5,
      "wind": 6.03,
      "cloud": 40.75,
      "rain": 0.0,
      "weathercode": 1,
      "fog_probability": 0.924,
      "castle_probability": 0.265,
      "castle_event_probability": 0.137,
      "event": "FogOnly"
    },
    {
      "date": "2026-07-08",
      "temp": 23.7,
      "humidity": 86.0,
      "wind": 12.0,
      "cloud": 76.0,
      "rain": 0.05,
      "weathercode": 51,
      "fog_probability": 0.087,
      "castle_probability": 0.167,
      "castle_event_probability": 0.003,
      "event": "None"
    },
    {
      "date": "2026-07-09",
      "temp": 24.27,
      "humidity": 87.25,
      "wind": 6.6,
      "cloud": 97.75,
      "rain": 0.0,
      "weathercode": 3,
      "fog_probability": 0.809,
      "castle_probability": 0.068,
      "castle_event_probability": 0.026,
      "event": "FogOnly"
    },
    {
      "date": "2026-07-10",
      "temp": 26.45,
      "humidity": 78.25,
      "wind": 7.53,
      "cloud": 13.0,
      "rain": 0.0,
      "weathercode": 0,
      "fog_probability": 0.924,
      "castle_probability": 0.377,
      "castle_event_probability": 0.261,
      "event": "FogOnly"
    },
    {
      "date": "2026-07-11",
      "temp": 27.62,
      "humidity": 73.25,
      "wind": 3.82,
      "cloud": 84.5,
      "rain": 0.0,
      "weathercode": 3,
      "fog_probability": 0.591,
      "castle_probability": 0.362,
      "castle_event_probability": 0.062,
      "event": "FogOnly"
    },
    {
      "date": "2026-07-12",
      "temp": 23.15,
      "humidity": 96.0,
      "wind": 2.88,
      "cloud": 100.0,
      "rain": 2.0,
      "weathercode": 95,
      "fog_probability": 0.048,
      "castle_probability": 0.135,
      "castle_event_probability": 0.003,
      "event": "None"
    },
    {
      "date": "2026-07-13",
      "temp": 23.7,
      "humidity": 97.25,
      "wind": 4.2,
      "cloud": 100.0,
      "rain": 0.1,
      "weathercode": 51,
      "fog_probability": 0.849,
      "castle_probability": 0.165,
      "castle_event_probability": 0.056,
      "event": "FogOnly"
    },
    {
      "date": "2026-07-14",
      "temp": 25.45,
      "humidity": 78.75,
      "wind": 2.95,
      "cloud": 86.0,
      "rain": 0.0,
      "weathercode": 3,
      "fog_probability": 0.765,
      "castle_probability": 0.124,
      "castle_event_probability": 0.032,
      "event": "FogOnly"
    },
    {
      "date": "2026-07-15",
      "temp": 25.9,
      "humidity": 75.0,
      "wind": 15.2,
      "cloud": 81.5,
      "rain": 0.0,
      "weathercode": 3,
      "fog_probability": 0.502,
      "castle_probability": 0.309,
      "castle_event_probability": 0.032,
      "event": "FogOnly"
    },
    {
      "date": "2026-07-16",
      "temp": 26.05,
      "humidity": 74.25,
      "wind": 12.27,
      "cloud": 88.5,
      "rain": 0.0,
      "weathercode": 3,
      "fog_probability": 0.608,
      "castle_probability": 0.106,
      "castle_event_probability": 0.017,
      "event": "FogOnly"
    },
    {
      "date": "2026-07-17",
      "temp": 25.07,
      "humidity": 71.25,
      "wind": 15.38,
      "cloud": 59.5,
      "rain": 0.0,
      "weathercode": 2,
      "fog_probability": 0.603,
      "castle_probability": 0.072,
      "castle_event_probability": 0.014,
      "event": "FogOnly"
    }
  ]
}