[
  {
    "date": "2026-06-02",
    "temp": 20.25,
    "humidity": 76.0,
    "wind": 9.85,
    "cloud": 96.25,
    "rain": 0.075,
    "weathercode": 3
  },
  {
    "date": "2026-06-03",
    "temp": 19.025000000000002,
    "humidity": 93.5,
    "wind": 5.625,
    "cloud": 100.0,
    "rain": 6.074999999999999,
    "weathercode": 63
  },
  {
    "date": "2026-06-04",
    "temp": 17.6,
    "humidity": 87.0,
    "wind": 2.175,
    "cloud": 45.75,
    "rain": 0.0,
    "weathercode": 1
  },
  {
    "date": "2026-06-05",
    "temp": 19.725,
    "humidity": 78.25,
    "wind": 10.25,
    "cloud": 3.25,
    "rain": 0.0,
    "weathercode": 0
  },
  {
    "date": "2026-06-06",
    "temp": 19.95,
    "humidity": 81.5,
    "wind": 6.050000000000001,
    "cloud": 96.25,
    "rain": 0.05,
    "weathercode": 51
  },
  {
    "date": "2026-06-07",
    "temp": 19.95,
    "humidity": 83.25,
    "wind": 5.35,
    "cloud": 32.25,
    "rain": 0.0,
    "weathercode": 1
  },
  {
    "date": "2026-06-08",
    "temp": 19.0,
    "humidity": 94.5,
    "wind": 4.025,
    "cloud": 99.75,
    "rain": 0.5,
    "weathercode": 53
  },
  {
    "date": "2026-06-09",
    "temp": 17.8,
    "humidity": 85.25,
    "wind": 5.8,
    "cloud": 68.5,
    "rain": 0.1,
    "weathercode": 51
  },
  {
    "date": "2026-06-10",
    "temp": 15.925,
    "humidity": 79.0,
    "wind": 1.925,
    "cloud": 66.0,
    "rain": 0.0,
    "weathercode": 2
  },
  {
    "date": "2026-06-11",
    "temp": 17.825000000000003,
    "humidity": 75.5,
    "wind": 2.75,
    "cloud": 36.25,
    "rain": 0.0,
    "weathercode": 1
  },
  {
    "date": "2026-06-12",
    "temp": 20.0,
    "humidity": 64.0,
    "wind": 3.7,
    "cloud": 8.0,
    "rain": 0.0,
    "weathercode": 0
  },
  {
    "date": "2026-06-13",
    "temp": 21.025,
    "humidity": 74.5,
    "wind": 14.0,
    "cloud": 100.0,
    "rain": 0.0,
    "weathercode": 3
  },
  {
    "date": "2026-06-14",
    "temp": 19.55,
    "humidity": 83.25,
    "wind": 2.0999999999999996,
    "cloud": 98.75,
    "rain": 0.0,
    "weathercode": 3
  },
  {
    "date": "2026-06-15",
    "temp": 22.025,
    "humidity": 77.25,
    "wind": 4.275,
    "cloud": 1.25,
    "rain": 0.0,
    "weathercode": 0
  }
]