[
  {
    "date": "2026-03-05",
    "temp": 2.175,
    "humidity": 78.5,
    "wind": 8.425,
    "cloud": 44.75,
    "rain": 0.0,
    "weathercode": 1
  },
  {
    "date": "2026-03-06",
    "temp": 3.65,
    "humidity": 70.0,
    "wind": 8.125,
    "cloud": 27.25,
    "rain": 0.0,
    "weathercode": 1
  },
  {
    "date": "2026-03-07",
    "temp": 4.55,
    "humidity": 92.0,
    "wind": 7.625000000000001,
    "cloud": 56.5,
    "rain": 0.17500000000000002,
    "weathercode": 51
  },
  {
    "date": "2026-03-08",
    "temp": 0.475,
    "humidity": 72.0,
    "wind": 7.775,
    "cloud": 65.25,
    "rain": 0.0,
    "weathercode": 2
  },
  {
    "date": "2026-03-09",
    "temp": 1.9749999999999999,
    "humidity": 62.0,
    "wind": 0.95,
    "cloud": 37.5,
    "rain": 0.0,
    "weathercode": 1
  },
  {
    "date": "2026-03-10",
    "temp": 2.625,
    "humidity": 82.5,
    "wind": 3.3,
    "cloud": 94.0,
    "rain": 0.25,
    "weathercode": 61
  },
  {
    "date": "2026-03-11",
    "temp": 1.375,
    "humidity": 68.0,
    "wind": 1.525,
    "cloud": 0.75,
    "rain": 0.0,
    "weathercode": 0
  },
  {
    "date": "2026-03-12",
    "temp": 2.25,
    "humidity": 80.25,
    "wind": 1.275,
    "cloud": 6.0,
    "rain": 0.0,
    "weathercode": 0
  },
  {
    "date": "2026-03-13",
    "temp": 0.75,
    "humidity": 73.25,
    "wind": 14.425,
    "cloud": 100.0,
    "rain": 0.2,
    "weathercode": 51
  },
  {
    "date": "2026-03-14",
    "temp": -1.8000000000000003,
    "humidity": 80.75,
    "wind": 3.3499999999999996,
    "cloud": 11.25,
    "rain": 0.0,
    "weathercode": 0
  },
  {
    "date": "2026-03-15",
    "temp": 2.1,
    "humidity": 84.75,
    "wind": 3.625,
    "cloud": 55.0,
    "rain": 0.0,
    "weathercode": 1
  },
  {
    "date": "2026-03-16",
    "temp": 2.5999999999999996,
    "humidity": 86.75,
    "wind": 5.65,
    "cloud": 100.0,
    "rain": 0.0,
    "weathercode": 3
  },
  {
    "date": "2026-03-17",
    "temp": 3.2,
    "humidity": 77.0,
    "wind": 8.575,
    "cloud": 85.75,
    "rain": 0.0,
    "weathercode": 3
  },
  {
    "date": "2026-03-18",
    "temp": 2.95,
    "humidity": 63.5,
    "wind": 8.85,
    "cloud": 53.75,
    "rain": 0.0,
    "weathercode": 1
  }
]