[
  {
    "date": "2026-03-19",
    "temp": 8.7,
    "humidity": 95.0,
    "wind": 8.575000000000001,
    "cloud": 78.25,
    "rain": 2.05,
    "weathercode": 3
  },
  {
    "date": "2026-03-20",
    "temp": 0.9,
    "humidity": 59.75,
    "wind": 3.9499999999999997,
    "cloud": 8.5,
    "rain": 0.0,
    "weathercode": 0
  },
  {
    "date": "2026-03-21",
    "temp": 1.525,
    "humidity": 73.25,
    "wind": 4.55,
    "cloud": 0.0,
    "rain": 0.0,
    "weathercode": 0
  },
  {
    "date": "2026-03-22",
    "temp": 4.3,
    "humidity": 67.5,
    "wind": 6.55,
    "cloud": 27.0,
    "rain": 0.0,
    "weathercode": 0
  },
  {
    "date": "2026-03-23",
    "temp": 9.2,
    "humidity": 76.25,
    "wind": 5.8999999999999995,
    "cloud": 45.75,
    "rain": 0.0,
    "weathercode": 1
  },
  {
    "date": "2026-03-24",
    "temp": 6.775,
    "humidity": 90.5,
    "wind": 2.675,
    "cloud": 97.75,
    "rain": 0.0,
    "weathercode": 3
  },
  {
    "date": "2026-03-25",
    "temp": 8.175,
    "humidity": 86.75,
    "wind": 2.7750000000000004,
    "cloud": 95.75,
    "rain": 0.0,
    "weathercode": 3
  },
  {
    "date": "2026-03-26",
    "temp": 10.475,
    "humidity": 83.0,
    "wind": 2.8249999999999997,
    "cloud": 75.5,
    "rain": 0.0,
    "weathercode": 3
  },
  {
    "date": "2026-03-27",
    "temp": 9.925,
    "humidity": 63.75,
    "wind": 11.05,
    "cloud": 100.0,
    "rain": 0.0,
    "weathercode": 3
  },
  {
    "date": "2026-03-28",
    "temp": 10.575,
    "humidity": 96.0,
    "wind": 7.6,
    "cloud": 100.0,
    "rain": 0.44999999999999996,
    "weathercode": 51
  },
  {
    "date": "2026-03-29",
    "temp": 6.999999999999999,
    "humidity": 86.25,
    "wind": 8.399999999999999,
    "cloud": 94.0,
    "rain": 0.1,
    "weathercode": 51
  },
  {
    "date": "2026-03-30",
    "temp": 5.699999999999999,
    "humidity": 69.25,
    "wind": 7.1,
    "cloud": 25.0,
    "rain": 0.0,
    "weathercode": 1
  },
  {
    "date": "2026-03-31",
    "temp": 7.5249999999999995,
    "humidity": 54.5,
    "wind": 5.7250000000000005,
    "cloud": 0.0,
    "rain": 0.0,
    "weathercode": 0
  },
  {
    "date": "2026-04-01",
    "temp": 11.05,
    "humidity": 59.25,
    "wind": 11.275,
    "cloud": 2.25,
    "rain": 0.0,
    "weathercode": 0
  }
]